tornado_smtp/client.py
tornado_smtp/__init__.py
tornado_smtp-0.1.1.dist-info/DESCRIPTION.rst
tornado_smtp-0.1.1.dist-info/METADATA
tornado_smtp-0.1.1.dist-info/metadata.json
tornado_smtp-0.1.1.dist-info/RECORD
tornado_smtp-0.1.1.dist-info/top_level.txt
tornado_smtp-0.1.1.dist-info/WHEEL
