Metadata-Version: 2.0
Name: tornado-smtp
Version: 0.1.1
Summary: An asynchronous SMTP client for Tornado
Home-page: https://github.com/rmoritz/tornado-smtp
Author: Ralph Moritz
Author-email: ralphmoritz@outlook.com
License: MIT
Requires-Dist: tornado (>=3.2.0)
